yta_image_edition_module/__init__.py
yta_image_edition_module/background.py
yta_image_edition_module/green_screen.py
yta_image_edition_module/resizer.py
yta_image_edition_module/sticker.py
yta_image_edition_module/utils.py
yta_image_edition_module/experimental/__init__.py
yta_image_edition_module/experimental/ascii_art.py
yta_image_edition_module/experimental/ascii_art_color.py
yta_image_edition_module/experimental/pixel_art.py
yta_image_edition_module/test/__init__.py
yta_image_edition_module-0.0.1.dist-info/LICENSE
yta_image_edition_module-0.0.1.dist-info/METADATA
yta_image_edition_module-0.0.1.dist-info/WHEEL
yta_image_edition_module-0.0.1.dist-info/top_level.txt
yta_image_edition_module-0.0.1.dist-info/RECORD
