Metadata-Version: 2.1
Name: yta-image-edition-module
Version: 0.0.1
Summary: Youtube Autónomo Image Edition module is here.
Home-page: UNKNOWN
Author: Daniel Alcalá
Author-email: <danielalcalavalera@gmail.com>
License: UNKNOWN
Keywords: youtube autonomo image edition utils module
Platform: UNKNOWN
Classifier: Development Status :: 3 - Alpha
Classifier: Intended Audience :: Education
Classifier: Programming Language :: Python :: 2
Classifier: Programming Language :: Python :: 3
Classifier: Operating System :: MacOS :: MacOS X
Classifier: Operating System :: Microsoft :: Windows
